LICENSE
MANIFEST.in
README.rst
setup.py
django_static_pages.egg-info/PKG-INFO
django_static_pages.egg-info/SOURCES.txt
django_static_pages.egg-info/dependency_links.txt
django_static_pages.egg-info/requires.txt
django_static_pages.egg-info/top_level.txt
static_pages/__init__.py
static_pages/models.py
static_pages/management/__init__.py
static_pages/management/commands/__init__.py
static_pages/management/commands/generate_static_pages.py
static_pages/tests/__init__.py
static_pages/tests/runner.py
static_pages/tests/tests.py
static_pages/tests/urls.py
static_pages/tests/views.py