Metadata-Version: 1.1
Name: django-static-pages
Version: 0.1.1
Summary: A reusable Django app that generates static pages using Django test client
Home-page: https://github.com/atugushev/django-static-pages
Author: Albert Tugushev
Author-email: albert@tugushev.ru
License: MIT License
Platform: UNKNOWN
Classifier: Development Status :: 4 - Beta
Classifier: Environment :: Web Environment
Classifier: Framework :: Django
Classifier: Intended Audience :: Developers
Classifier: License :: OSI Approved :: MIT License
Classifier: Programming Language :: Python
